paxful/__init__.py
paxful/exceptions.py
paxful/main_client.py
paxful/paxful_rest.py
paxful/trade_client.py
paxful_api-1.0.1.dist-info/LICENSE
paxful_api-1.0.1.dist-info/METADATA
paxful_api-1.0.1.dist-info/WHEEL
paxful_api-1.0.1.dist-info/top_level.txt
paxful_api-1.0.1.dist-info/RECORD
