Metadata-Version: 2.1
Name: paxful-api
Version: 1.0.1
Summary: A python wrapper for Paxful REST API v1
Home-page: https://github.com/tholness/Paxful-API-Wrapper
Author: tholness
Author-email: support.ec1818@tryninja.io
License: UNKNOWN
Platform: UNKNOWN
Classifier: Programming Language :: Python :: 3
Classifier: License :: OSI Approved :: MIT License
Classifier: Operating System :: OS Independent
Requires-Python: >=3.6
Requires-Dist: requests (>=2.23.0)
Requires-Dist: simplejson (>=3.17.0)
